MANIFEST.in
README.rst
entry_points.ini
setup.cfg
setup.py
src/AnthraxHTMLInput.egg-info/PKG-INFO
src/AnthraxHTMLInput.egg-info/SOURCES.txt
src/AnthraxHTMLInput.egg-info/dependency_links.txt
src/AnthraxHTMLInput.egg-info/entry_points.txt
src/AnthraxHTMLInput.egg-info/namespace_packages.txt
src/AnthraxHTMLInput.egg-info/requires.txt
src/AnthraxHTMLInput.egg-info/top_level.txt
src/anthrax/__init__.py
src/anthrax/html_input/__init__.py
src/anthrax/html_input/field.py
src/anthrax/html_input/widget.py